nextmcp/__init__.py
nextmcp/cli.py
nextmcp/config.py
nextmcp/core.py
nextmcp/discovery.py
nextmcp/logging.py
nextmcp/middleware.py
nextmcp/plugins.py
nextmcp/prompts.py
nextmcp/py.typed
nextmcp/resources.py
nextmcp/tools.py
nextmcp/auth/__init__.py
nextmcp/auth/core.py
nextmcp/auth/errors.py
nextmcp/auth/manifest.py
nextmcp/auth/middleware.py
nextmcp/auth/oauth.py
nextmcp/auth/oauth_providers.py
nextmcp/auth/providers.py
nextmcp/auth/rbac.py
nextmcp/auth/request_middleware.py
nextmcp/deployment/__init__.py
nextmcp/deployment/health.py
nextmcp/deployment/lifecycle.py
nextmcp/deployment/templates.py
nextmcp/metrics/__init__.py
nextmcp/metrics/collector.py
nextmcp/metrics/config.py
nextmcp/metrics/middleware.py
nextmcp/metrics/registry.py
nextmcp/metrics/types.py
nextmcp/metrics/exporters/__init__.py
nextmcp/metrics/exporters/json_exporter.py
nextmcp/metrics/exporters/prometheus.py
nextmcp/protocol/__init__.py
nextmcp/protocol/auth_metadata.py
nextmcp/security/__init__.py
nextmcp/security/validation.py
nextmcp/session/__init__.py
nextmcp/session/session_store.py
nextmcp/transport/__init__.py
nextmcp/transport/websocket.py
nextmcp/transport/ws_client.py
nextmcp-0.6.0.dist-info/licenses/LICENSE
nextmcp-0.6.0.dist-info/METADATA
nextmcp-0.6.0.dist-info/WHEEL
nextmcp-0.6.0.dist-info/entry_points.txt
nextmcp-0.6.0.dist-info/top_level.txt
nextmcp-0.6.0.dist-info/RECORD
