Metadata-Version: 2.4
Name: nextmcp
Version: 0.6.0
Summary: Production-grade MCP server toolkit with minimal boilerplate
Home-page: https://github.com/KeshavVarad/NextMCP
Author: NextMCP Contributors
License: MIT
Project-URL: Homepage, https://github.com/KeshavVarad/NextMCP
Project-URL: Documentation, https://github.com/KeshavVarad/NextMCP#readme
Project-URL: Repository, https://github.com/KeshavVarad/NextMCP
Project-URL: Issues, https://github.com/KeshavVarad/NextMCP/issues
Keywords: mcp,server,sdk,fastmcp,framework
Classifier: Development Status :: 3 - Alpha
Classifier: Intended Audience :: Developers
Classifier: Programming Language :: Python :: 3
Classifier: Programming Language :: Python :: 3.10
Classifier: Programming Language :: Python :: 3.11
Classifier: Programming Language :: Python :: 3.12
Classifier: Programming Language :: Python :: 3.13
Classifier: Topic :: Software Development :: Libraries :: Python Modules
Classifier: Topic :: Internet :: WWW/HTTP :: HTTP Servers
Requires-Python: >=3.8
License-File: LICENSE
Requires-Dist: fastmcp>=0.1.0
Requires-Dist: aiohttp>=3.8.0
Provides-Extra: dev
Requires-Dist: pytest>=7.0.0; extra == "dev"
Requires-Dist: pytest-cov>=4.0.0; extra == "dev"
Requires-Dist: pytest-asyncio>=0.21.0; extra == "dev"
Requires-Dist: black>=23.0.0; extra == "dev"
Requires-Dist: ruff>=0.1.0; extra == "dev"
Requires-Dist: mypy>=1.0.0; extra == "dev"
Provides-Extra: cli
Requires-Dist: typer>=0.9.0; extra == "cli"
Requires-Dist: rich>=13.0.0; extra == "cli"
Provides-Extra: config
Requires-Dist: python-dotenv>=1.0.0; extra == "config"
Requires-Dist: pyyaml>=6.0.0; extra == "config"
Provides-Extra: schema
Requires-Dist: pydantic>=2.0.0; extra == "schema"
Provides-Extra: websocket
Requires-Dist: websockets>=12.0; extra == "websocket"
Provides-Extra: all
Requires-Dist: nextmcp[cli,config,dev,schema,websocket]; extra == "all"
Dynamic: home-page
Dynamic: license-file
Dynamic: requires-python
